data_acquisition_api/__init__.py
data_acquisition_api/data_acquisition_pb2.py
data_acquisition_api/data_acquisition_pb2_grpc.py
data_acquisition_api/robot_pb2.py
data_acquisition_api/robot_pb2_grpc.py
data_acquisition_api/teleoperator_pb2.py
data_acquisition_api/teleoperator_pb2_grpc.py
pollen_data_acquisition_api-0.0.1.dist-info/METADATA
pollen_data_acquisition_api-0.0.1.dist-info/WHEEL
pollen_data_acquisition_api-0.0.1.dist-info/top_level.txt
pollen_data_acquisition_api-0.0.1.dist-info/RECORD
