Metadata-Version: 2.1
Name: pollen-data-acquisition-api
Version: 0.0.1
Summary: gRPC Protobuf API definition for Robot data acquisition pipeline using LeRobot
Home-page: https://github.com/pollen-robotics/data-acquisition-api
Author: Pollen Robotics
Author-email: contact@pollen-robotics.com
Requires-Dist: grpcio<=1.70.0,>=1.59.0
Requires-Dist: grpcio-tools<=1.62.2,>=1.59.0
Requires-Dist: protobuf<=5.29.3,>=4.25.0
